csv_progressbar/__init__.py
csv_progressbar/pbar_csv.py
csv_progressbar/pbar_protocol.py
csv_progressbar-0.1.dist-info/LICENSE
csv_progressbar-0.1.dist-info/METADATA
csv_progressbar-0.1.dist-info/WHEEL
csv_progressbar-0.1.dist-info/top_level.txt
csv_progressbar-0.1.dist-info/RECORD
