Metadata-Version: 2.1
Name: csv-progressbar
Version: 0.1
Summary: A progressbar wrapper for standart csv package
Author: chazovtema
Author-email: chazovtema@mail.ru
Project-URL: github, https://github.com/chazovtema/CSVProgressBar
Keywords: csv,progressbar
Classifier: Programming Language :: Python :: 3.10
Classifier: License :: OSI Approved :: MIT License
Classifier: Operating System :: OS Independent
Requires-Python: >=3.10
License-File: LICENSE
